[{"weights":[{"name":"conv0/filters","shape":[3,3,3,16],"dtype":"float32","quantization":{"dtype":"uint8","scale":0.009007044399485869,"min":-1.2069439495310063}},{"name":"conv0/bias","shape":[16],"dtype":"float32","quantization":{"dtype":"uint8","scale":0.004798682906404909,"min":-0.8109174112424496}},{"name":"conv1/depthwise_filter","shape":[3,3,16,1],"dtype":"float32","quantization":{"dtype":"uint8","scale":0.004001977630690033,"min":-0.5042491814669441}},{"name":"conv1/pointwise_filter","shape":[1,1,16,32],"dtype":"float32","quantization":{"dtype":"uint8","scale":0.013836609615999109,"min":-1.7849427106138951}},{"name":"conv1/bias","shape":[32],"dtype":"float32","quantization":{"dtype":"uint8","scale":0.0022336944412645975,"min":-0.3216519195421021}},{"name":"conv2/depthwise_filter","shape":[3,3,32,1],"dtype":"float32","quantization":{"dtype":"uint8","scale":0.002716888457553832,"min":-0.3286434633640037}},{"name":"conv2/pointwise_filter","shape":[1,1,32,64],"dtype":"float32","quantization":{"dtype":"uint8","scale":0.015265831292372941,"min":-1.923694542838791}},{"name":"conv2/bias","shape":[64],"dtype":"float32","quantization":{"dtype":"uint8","scale":0.0023670422811062925,"min":-0.31957070794934947}},{"name":"conv3/depthwise_filter","shape":[3,3,64,1],"dtype":"float32","quantization":{"dtype":"uint8","scale":0.003387439561248619,"min":-0.4642492098910608}},{"name":"conv3/pointwise_filter","shape":[1,1,64,128],"dtype":"float32","quantization":{"dtype":"uint8","scale":0.016646602487863554,"min":-2.163058323422262}},{"name":"conv3/bias","shape":[128],"dtype":"float32","quantization":{"dtype":"uint8","scale":0.003539431952821155,"min":-0.6724920710360195}},{"name":"conv4/depthwise_filter","shape":[3,3,128,1],"dtype":"float32","quantization":{"dtype":"uint8","scale":0.0025917134891608947,"min":-0.32914761312042964}},{"name":"conv4/pointwise_filter","shape":[1,1,128,256],"dtype":"float32","quantization":{"dtype":"uint8","scale":0.021875603993733724,"min":-2.8875797271728517}},{"name":"conv4/bias","shape":[256],"dtype":"float32","quantization":{"dtype":"uint8","scale":0.0041141652009066276,"min":-0.6583664321450604}},{"name":"conv5/depthwise_filter","shape":[3,3,256,1],"dtype":"float32","quantization":{"dtype":"uint8","scale":0.004834806478748492,"min":-0.7203861653535053}},{"name":"conv5/pointwise_filter","shape":[1,1,256,512],"dtype":"float32","quantization":{"dtype":"uint8","scale":0.030007277283014035,"min":-3.8709387695288107}},{"name":"conv5/bias","shape":[512],"dtype":"float32","quantization":{"dtype":"uint8","scale":0.008402082966823203,"min":-1.2351662061430507}},{"name":"conv8/filters","shape":[1,1,512,25],"dtype":"float32","quantization":{"dtype":"uint8","scale":0.028336129469030042,"min":-4.675461862389957}},{"name":"conv8/bias","shape":[25],"dtype":"float32","quantization":{"dtype":"uint8","scale":0.002268134028303857,"min":-0.41053426912599815}}],"paths":["tiny_face_detector_model.weights"]}]